<?xml version="1.0" encoding="utf-8"?>
<Formular_Data xmlns:xsi="http://www.w3.org/2001/XMLSchema-instance" xmlns:xsd="http://www.w3.org/2001/XMLSchema" DateTimeValue="2018-01-19">
  <AccessDatabase></AccessDatabase>
  <ChkAccess>true</ChkAccess>
  <ChkSde>false</ChkSde>
  <ChkAuthentifizierung>false</ChkAuthentifizierung>
  <SqlServer></SqlServer>
  <ServerInstance></ServerInstance>
  <ServerDatenbank></ServerDatenbank>
  <ServerUser />
  <ServerPasswort />
  <ServerVersion>SDE.DEFAULT</ServerVersion>
  <LegendTables>    
  </LegendTables>
  <Table></Table>
  <TabAccess>true</TabAccess>
  <TabSde>false</TabSde>
  <DatabaseId>ID</DatabaseId>
  <Sortierschluessel>L_SORT</Sortierschluessel>
  <Legendentext>L_TEXT</Legendentext>
  <Zeichenelemente>L_SYMB</Zeichenelemente>
  <Legendengrafik>L_GRAPHICS</Legendengrafik>
  <ChkLegendengrafik>true</ChkLegendengrafik>
  <Ueberschrift1>HEADING1</Ueberschrift1>
  <ChkUeberschrift1>true</ChkUeberschrift1>
  <Ueberschrift2>HEADING2</Ueberschrift2>
  <ChkUeberschrift2>true</ChkUeberschrift2>
  <Ueberschrift3>HEADING3</Ueberschrift3>
  <ChkUeberschrift3>true</ChkUeberschrift3>
  <Klammerebene1>BRACKET1</Klammerebene1>
  <ChkKlammerebene1>true</ChkKlammerebene1>
  <Klammerebene2>BRACKET2</Klammerebene2>
  <ChkKlammerebene2>true</ChkKlammerebene2>
  <Klammerebene3>BRACKET3</Klammerebene3>
  <ChkKlammerebene3>true</ChkKlammerebene3>
  <Gruppierung>L_GROUP</Gruppierung>
  <ChkGruppierung>true</ChkGruppierung>
  <Flaechensymbolname>FILL_SYMBOL</Flaechensymbolname>
  <ChkFlaechensymbolname>true</ChkFlaechensymbolname>
  <Liniensymbolname>LINE_SYMBOL</Liniensymbolname>
  <ChkLiniensymbolname>true</ChkLiniensymbolname>
  <Markersymbolname>MARKER_SYMBOL</Markersymbolname>
  <ChkMarkersymbolname>true</ChkMarkersymbolname>
  <Legendennummer>L_NUM</Legendennummer>
  <ChkLegendennummer>true</ChkLegendennummer>
  <ChkFortlaufendeNummer>false</ChkFortlaufendeNummer>
  <FortlaufendeNummer>fortlaufendeNummer.txt</FortlaufendeNummer>
  <Infozeile4>HEADING4</Infozeile4>
  <ChkInfozeile4>false</ChkInfozeile4>
  <Infozeile5>HEADING5</Infozeile5>
  <ChkInfozeile5>false</ChkInfozeile5>
  <Infozeile6>HEADING6</Infozeile6>
  <ChkInfozeile6>false</ChkInfozeile6>
  <Notizen>NOTES</Notizen>
  <ChkNotizen>false</ChkNotizen>
  <ChkSpatialQuery>false</ChkSpatialQuery>
  <SpatialQueryId>GBANR</SpatialQueryId>
  <AttributeQuery />
  <ChkFarbwerte>false</ChkFarbwerte>
  <ChkAllowNullLegendNumber>false</ChkAllowNullLegendNumber>
  <ChkGifExport>false</ChkGifExport>
  <XOffset>10</XOffset>
  <YOffset>3</YOffset>
  <Vertikalabstand>0,3</Vertikalabstand>
  <Klammerabstand>0,4</Klammerabstand>
  <KaestchenLegendentextAbstand>0,4</KaestchenLegendentextAbstand>
  <VorUeberschrift1>0,4</VorUeberschrift1>
  <NachUeberschrift1>0,6</NachUeberschrift1>
  <NachUeberschrift2>0,6</NachUeberschrift2>
  <NotizenOffset>9</NotizenOffset>
  <UmbruchUeberschrift1>40</UmbruchUeberschrift1>
  <UmbruchUeberschrift2>40</UmbruchUeberschrift2>
  <UmbruchUeberschrift3>40</UmbruchUeberschrift3>
  <UmbruchLegendentext>50</UmbruchLegendentext>
  <UmbruchSpaltenLaenge>50</UmbruchSpaltenLaenge>
  <UmbruchSpaltenOffset>12</UmbruchSpaltenOffset>
  <Roc>0</Roc>
  <Rom>100</Rom>
  <Roy>100</Roy>
  <Rok>21</Rok>
  <Blc>70</Blc>
  <Blm>30</Blm>
  <Bly>0</Bly>
  <Blk>21</Blk>
  <Grc>70</Grc>
  <Grm>0</Grm>
  <Gry>100</Gry>
  <Grk>21</Grk>
  <Brc>20</Brc>
  <Brm>50</Brm>
  <Bry>60</Bry>
  <Brk>21</Brk>
  <Gac>10</Gac>
  <Gam>10</Gam>
  <Gay>10</Gay>
  <Gak>21</Gak>
  <Mac>0</Mac>
  <Mam>100</Mam>
  <May>0</May>
  <Mak>21</Mak>
  <Cyc>100</Cyc>
  <Cym>0</Cym>
  <Cyy>0</Cyy>
  <Cyk>21</Cyk>
  <Gec>0</Gec>
  <Gem>0</Gem>
  <Gey>100</Gey>
  <Gek>21</Gek>
  <Orc>0</Orc>
  <Orm>30</Orm>
  <Ory>100</Ory>
  <Ork>21</Ork>
</Formular_Data>